{
  "type": "Feature",
  "properties": {
    "gn:admin1_code":"03",
    "gn:asciiname":"Kas N'Jaibal",
    "gn:country_code":"GM",
    "gn:dem":43,
    "gn:feature_class":"P",
    "gn:feature_code":"PPL",
    "gn:name":"Kas N\u2019Jaibal",
    "gn:population":0,
    "gn:timezone":"Africa/Banjul",
    "iso:country":"GM",
    "name:und_x_variant":[
        "Kass N\u2019Jaibal",
        "Kas N\u2019Jaibal"
    ],
    "wof:name":"Kas N'Jaibal",
    "wof:placetype":"locality"
},
  "geometry": {"coordinates":[-14.93333,13.76667],"type":"Point"}
}