{
  "type": "Feature",
  "properties": {
    "gn:admin1_code":"03",
    "gn:asciiname":"Sondeh Densay",
    "gn:country_code":"GM",
    "gn:dem":19,
    "gn:feature_class":"P",
    "gn:feature_code":"PPL",
    "gn:name":"Sondeh Densay",
    "gn:population":0,
    "gn:timezone":"Africa/Banjul",
    "iso:country":"GM",
    "wof:name":"Sondeh Densay",
    "wof:placetype":"locality"
},
  "geometry": {"coordinates":[-15.31667,13.55],"type":"Point"}
}