{
  "type": "Feature",
  "properties": {
    "gn:country":"GM",
    "gn:fcode":"PPL",
    "gn:population":282,
    "iso:country":"GM",
    "qs:name":"Dandugu",
    "qs:photos_9r":0,
    "qs:photos_sr":0,
    "qs:pop_sr":"2",
    "wof:name":"Dandugu",
    "wof:placetype":"locality",
    "wof:population":282
},
  "geometry": {"coordinates":[-14.13333,13.28333],"type":"Point"}
}