{
  "type": "Feature",
  "properties": {
    "gn:country":"GM",
    "gn:fcode":"PPL",
    "gn:population":87,
    "iso:country":"GM",
    "qs:name":"Sare Ganya",
    "qs:photos_9r":0,
    "qs:photos_sr":0,
    "qs:pop_sr":"1",
    "wof:name":"Sare Ganya",
    "wof:placetype":"locality",
    "wof:population":87
},
  "geometry": {"coordinates":[-14.48333,13.33333],"type":"Point"}
}