{
  "type": "Feature",
  "properties": {
    "gn:country":"GM",
    "gn:fcode":"PPL",
    "gn:population":230,
    "iso:country":"GM",
    "qs:name":"Jomarr",
    "qs:photos_9r":0,
    "qs:photos_sr":0,
    "qs:pop_sr":"2",
    "wof:name":"Jomarr",
    "wof:placetype":"locality",
    "wof:population":230
},
  "geometry": {"coordinates":[-15.66667,13.43333],"type":"Point"}
}