{
  "type": "Feature",
  "properties": {
    "gn:admin1_code":"04",
    "gn:asciiname":"Sare Sambaru",
    "gn:country_code":"GM",
    "gn:dem":39,
    "gn:feature_class":"P",
    "gn:feature_code":"PPL",
    "gn:name":"Sare Sambaru",
    "gn:population":0,
    "gn:timezone":"Africa/Banjul",
    "iso:country":"GM",
    "wof:name":"Sare Sambaru",
    "wof:placetype":"locality"
},
  "geometry": {"coordinates":[-14.41667,13.45],"type":"Point"}
}