{
  "type": "Feature",
  "properties": {
    "gn:country":"GM",
    "gn:fcode":"PPL",
    "gn:pop":36,
    "iso:country":"GM",
    "qs:name":"Tankanto",
    "qs:photos_9r":0,
    "qs:photos_sr":0,
    "qs:pop_sr":"1",
    "wof:name":"Tankanto",
    "wof:placetype":"locality",
    "wof:population":36
},
  "geometry": {"coordinates":[-15.66667,13.53333],"type":"Point"}
}