{
  "type": "Feature",
  "properties": {
    "gn:admin1_code":"03",
    "gn:asciiname":"Madina Mbaien",
    "gn:country_code":"GM",
    "gn:dem":21,
    "gn:feature_class":"P",
    "gn:feature_code":"PPL",
    "gn:name":"Madina Mbaien",
    "gn:population":0,
    "gn:timezone":"Africa/Banjul",
    "iso:country":"GM",
    "wof:name":"Madina Mbaien",
    "wof:placetype":"locality"
},
  "geometry": {"coordinates":[-15.06667,13.75],"type":"Point"}
}