{
  "type": "Feature",
  "properties": {
    "iso:country":"GM",
    "name:ara_x_preferred":[
        "\u0628\u0627\u0643\u0627\u0648"
    ],
    "name:bre_x_preferred":[
        "Bakau"
    ],
    "name:ceb_x_preferred":[
        "Bakau"
    ],
    "name:ces_x_preferred":[
        "Bakau"
    ],
    "name:cos_x_preferred":[
        "Bakau"
    ],
    "name:dan_x_preferred":[
        "Bakau"
    ],
    "name:deu_x_preferred":[
        "Bakau"
    ],
    "name:eng_x_preferred":[
        "Bakau"
    ],
    "name:fin_x_preferred":[
        "Bakau"
    ],
    "name:fra_x_preferred":[
        "Bakau"
    ],
    "name:heb_x_preferred":[
        "\u05d1\u05e7\u05d0\u05d5"
    ],
    "name:hun_x_preferred":[
        "Bakau"
    ],
    "name:ind_x_preferred":[
        "Bakau"
    ],
    "name:ita_x_preferred":[
        "Bakau"
    ],
    "name:jpn_x_preferred":[
        "\u30d0\u30ab\u30a6"
    ],
    "name:kor_x_preferred":[
        "\ubc14\uce74\uc6b0"
    ],
    "name:lit_x_preferred":[
        "Bakau"
    ],
    "name:nds_x_preferred":[
        "Bakau"
    ],
    "name:nld_x_preferred":[
        "Bakau"
    ],
    "name:nob_x_preferred":[
        "Bakau"
    ],
    "name:pol_x_preferred":[
        "Bakau"
    ],
    "name:por_x_preferred":[
        "Bakau"
    ],
    "name:ron_x_preferred":[
        "Bakau"
    ],
    "name:rus_x_preferred":[
        "\u0411\u0430\u043a\u0430\u0443"
    ],
    "name:slv_x_preferred":[
        "Bakau"
    ],
    "name:spa_x_preferred":[
        "Bakau"
    ],
    "name:swe_x_preferred":[
        "Bakau"
    ],
    "name:tah_x_preferred":[
        "Bakau"
    ],
    "name:zho_x_preferred":[
        "\u5df4\u8003"
    ],
    "qs:gn_country":"GM",
    "qs:gn_fcode":"PPL",
    "qs:gn_pop":43098,
    "qs:name":"Bakau",
    "qs:name_adm0":"The Gambia",
    "qs:photos":1147,
    "qs:photos_1k":232,
    "qs:photos_9k":5,
    "qs:photos_9r":7,
    "qs:photos_all":1147,
    "qs:photos_sr":11,
    "qs:placetype":"Town",
    "qs:pop_sr":"7",
    "qs:woe_adm0":23424821,
    "wd:wordcount":592,
    "wof:name":"Bakau",
    "wof:placetype":"locality",
    "wof:population":43098
},
  "geometry": {"coordinates":[-16.68194,13.47806],"type":"Point"}
}