{
  "type": "Feature",
  "properties": {
    "gn:country":"GM",
    "gn:fcode":"PPL",
    "gn:population":913,
    "iso:country":"GM",
    "name:und_x_variant":[
        "Tankural"
    ],
    "qs:name":"Tankular",
    "qs:photos_9r":0,
    "qs:photos_sr":0,
    "qs:pop_sr":"2",
    "wof:name":"Tankular",
    "wof:placetype":"locality",
    "wof:population":913
},
  "geometry": {"coordinates":[-16.03694,13.41778],"type":"Point"}
}