{
  "type": "Feature",
  "properties": {
    "gn:admin1_code":"05",
    "gn:asciiname":"Sambuya",
    "gn:country_code":"GM",
    "gn:dem":25,
    "gn:feature_class":"P",
    "gn:feature_code":"PPL",
    "gn:name":"Sambuya",
    "gn:population":0,
    "gn:timezone":"Africa/Banjul",
    "iso:country":"GM",
    "wof:name":"Sambuya",
    "wof:placetype":"locality"
},
  "geometry": {"coordinates":[-16.7575,13.20917],"type":"Point"}
}