{
  "type": "Feature",
  "properties": {
    "gn:admin1_code":"05",
    "gn:asciiname":"Gikis Dandon",
    "gn:cc2":"GM",
    "gn:country_code":"GM",
    "gn:dem":33,
    "gn:feature_class":"P",
    "gn:feature_code":"PPL",
    "gn:name":"Gikis Dandon",
    "gn:population":0,
    "gn:timezone":"Africa/Banjul",
    "iso:country":"GM",
    "name:und_x_variant":[
        "Gikis",
        "Gikis Dandon"
    ],
    "wof:name":"Gikis Dandon",
    "wof:placetype":"locality"
},
  "geometry": {"coordinates":[-16.06639,13.17056],"type":"Point"}
}