{
  "type": "Feature",
  "properties": {
    "gn:country":"GM",
    "gn:fcode":"PPL",
    "gn:population":45,
    "iso:country":"GM",
    "qs:name":"Njoben Samba Narr Bah",
    "qs:photos_9r":0,
    "qs:photos_sr":0,
    "qs:pop_sr":"1",
    "wof:name":"Njoben Samba Narr Bah",
    "wof:placetype":"locality",
    "wof:population":45
},
  "geometry": {"coordinates":[-15.35,13.71667],"type":"Point"}
}