{
  "type": "Feature",
  "properties": {
    "gn:admin1_code":"05",
    "gn:asciiname":"Bator Sateh",
    "gn:cc2":"GM",
    "gn:country_code":"GM",
    "gn:dem":1,
    "gn:feature_class":"P",
    "gn:feature_code":"PPL",
    "gn:name":"Bator Sateh",
    "gn:population":0,
    "gn:timezone":"Africa/Banjul",
    "iso:country":"GM",
    "name:und_x_variant":[
        "Batori Sateh",
        "Bator Sateh"
    ],
    "wof:name":"Bator Sateh",
    "wof:placetype":"locality"
},
  "geometry": {"coordinates":[-16.77889,13.15306],"type":"Point"}
}