{
  "type": "Feature",
  "properties": {
    "gn:admin1_code":"05",
    "gn:asciiname":"Kusamai",
    "gn:cc2":"GM",
    "gn:country_code":"GM",
    "gn:dem":36,
    "gn:feature_class":"P",
    "gn:feature_code":"PPL",
    "gn:name":"Kusamai",
    "gn:population":0,
    "gn:timezone":"Africa/Banjul",
    "iso:country":"GM",
    "name:und_x_variant":[
        "Kossema",
        "Kussamai",
        "Kusamai"
    ],
    "wof:name":"Kusamai",
    "wof:placetype":"locality"
},
  "geometry": {"coordinates":[-16.17556,13.17306],"type":"Point"}
}