{
  "type": "Feature",
  "properties": {
    "gn:admin1_code":"07",
    "gn:asciiname":"Toro Mbaien",
    "gn:cc2":"GM",
    "gn:country_code":"GM",
    "gn:dem":13,
    "gn:feature_class":"P",
    "gn:feature_code":"PPL",
    "gn:name":"Toro Mbaien",
    "gn:population":0,
    "gn:timezone":"Africa/Banjul",
    "iso:country":"GM",
    "name:und_x_variant":[
        "N\u2019Toro Baien",
        "Toro Mbaien"
    ],
    "wof:name":"Toro Mbaien",
    "wof:placetype":"locality"
},
  "geometry": {"coordinates":[-16.07056,13.55806],"type":"Point"}
}