{
  "type": "Feature",
  "properties": {
    "gn:admin1_code":"07",
    "gn:asciiname":"Ginak Niji",
    "gn:cc2":"GM",
    "gn:country_code":"GM",
    "gn:dem":10,
    "gn:feature_class":"P",
    "gn:feature_code":"PPL",
    "gn:name":"Ginak Niji",
    "gn:population":0,
    "gn:timezone":"Africa/Banjul",
    "iso:country":"GM",
    "name:und_x_variant":[
        "Niji",
        "Ginak Niji"
    ],
    "wof:name":"Ginak Niji",
    "wof:placetype":"locality"
},
  "geometry": {"coordinates":[-16.525,13.57444],"type":"Point"}
}