{
  "type": "Feature",
  "properties": {
    "gn:admin1_code":"05",
    "gn:asciiname":"Kunkujang",
    "gn:country_code":"GM",
    "gn:dem":26,
    "gn:feature_class":"P",
    "gn:feature_code":"PPL",
    "gn:name":"Kunkujang",
    "gn:population":0,
    "gn:timezone":"Africa/Banjul",
    "iso:country":"GM",
    "wof:name":"Kunkujang",
    "wof:placetype":"locality"
},
  "geometry": {"coordinates":[-16.67278,13.38972],"type":"Point"}
}