{
  "type": "Feature",
  "properties": {
    "gn:admin1_code":"07",
    "gn:asciiname":"Jamagen",
    "gn:country_code":"GM",
    "gn:dem":19,
    "gn:feature_class":"P",
    "gn:feature_code":"PPL",
    "gn:name":"Jamagen",
    "gn:population":0,
    "gn:timezone":"Africa/Banjul",
    "iso:country":"GM",
    "name:und_x_variant":[
        "Jama Ken",
        "Jamagen"
    ],
    "wof:name":"Jamagen",
    "wof:placetype":"locality"
},
  "geometry": {"coordinates":[-16.25306,13.53361],"type":"Point"}
}