{
  "type": "Feature",
  "properties": {
    "gn:admin1_code":"07",
    "gn:asciiname":"Mbaien",
    "gn:country_code":"GM",
    "gn:dem":19,
    "gn:feature_class":"P",
    "gn:feature_code":"PPL",
    "gn:name":"Mbaien",
    "gn:population":0,
    "gn:timezone":"Africa/Banjul",
    "iso:country":"GM",
    "wof:name":"Mbaien",
    "wof:placetype":"locality"
},
  "geometry": {"coordinates":[-15.61667,13.53333],"type":"Point"}
}