{
  "type": "Feature",
  "properties": {
    "gn:admin1_code":"03",
    "gn:asciiname":"Sare Madi",
    "gn:country_code":"GM",
    "gn:dem":50,
    "gn:feature_class":"P",
    "gn:feature_code":"PPL",
    "gn:name":"Sare Madi",
    "gn:population":0,
    "gn:timezone":"Africa/Banjul",
    "iso:country":"GM",
    "wof:name":"Sare Madi",
    "wof:placetype":"locality"
},
  "geometry": {"coordinates":[-14.73333,13.41667],"type":"Point"}
}