{
  "type": "Feature",
  "properties": {
    "gn:admin1_code":"07",
    "gn:asciiname":"Jowara",
    "gn:country_code":"GM",
    "gn:dem":11,
    "gn:feature_class":"P",
    "gn:feature_code":"PPL",
    "gn:name":"Jowara",
    "gn:population":0,
    "gn:timezone":"Africa/Banjul",
    "iso:country":"GM",
    "wof:name":"Jowara",
    "wof:placetype":"locality"
},
  "geometry": {"coordinates":[-16.08,13.57667],"type":"Point"}
}