{
  "type": "Feature",
  "properties": {
    "iso:country":"GM",
    "qs:gn_country":"GM",
    "qs:gn_fcode":"PPL",
    "qs:gn_pop":168,
    "qs:name":"Beretto",
    "qs:name_adm0":"The Gambia",
    "qs:name_adm1":"North Bank",
    "qs:photos":0,
    "qs:photos_1k":0,
    "qs:photos_9k":0,
    "qs:photos_9r":0,
    "qs:photos_all":0,
    "qs:photos_sr":0,
    "qs:placetype":"Town",
    "qs:pop_sr":"1",
    "qs:woe_adm0":23424821,
    "wof:name":"Beretto",
    "wof:placetype":"locality",
    "wof:population":168
},
  "geometry": {"coordinates":[-15.58333,13.55],"type":"Point"}
}