{
  "type": "Feature",
  "properties": {
    "gn:country":"GM",
    "gn:fcode":"PPL",
    "gn:pop":1024,
    "iso:country":"GM",
    "qs:name":"Jali",
    "qs:photos_9r":0,
    "qs:photos_sr":0,
    "qs:pop_sr":"3",
    "wd:wordcount":328,
    "wof:name":"Jali",
    "wof:placetype":"locality",
    "wof:population":1024
},
  "geometry": {"coordinates":[-15.96667,13.35],"type":"Point"}
}