{
  "type": "Feature",
  "properties": {
    "gn:country":"GM",
    "gn:fcode":"PPL",
    "gn:population":1024,
    "iso:country":"GM",
    "name:ara_x_preferred":[
        "\u062c\u0627\u0644\u064a"
    ],
    "name:deu_x_preferred":[
        "Jali"
    ],
    "name:eng_x_preferred":[
        "jali"
    ],
    "name:epo_x_preferred":[
        "Jalio"
    ],
    "name:fra_x_preferred":[
        "jali"
    ],
    "name:guj_x_preferred":[
        "\u0a9c\u0abe\u0ab3\u0ac0"
    ],
    "name:hin_x_preferred":[
        "\u091c\u093e\u0932"
    ],
    "name:ita_x_preferred":[
        "jali"
    ],
    "name:mkd_x_preferred":[
        "\u045f\u0430\u043b\u0438"
    ],
    "name:nld_x_preferred":[
        "Jali"
    ],
    "name:por_x_preferred":[
        "jali"
    ],
    "name:san_x_preferred":[
        "\u091c\u093e\u0932"
    ],
    "qs:name":"Jali",
    "qs:photos_9r":0,
    "qs:photos_sr":0,
    "qs:pop_sr":"3",
    "wd:wordcount":328,
    "wof:name":"Jali",
    "wof:placetype":"locality",
    "wof:population":1024
},
  "geometry": {"coordinates":[-15.96667,13.35],"type":"Point"}
}