{
  "type": "Feature",
  "properties": {
    "gn:admin1_code":"05",
    "gn:asciiname":"Bonto",
    "gn:country_code":"GM",
    "gn:dem":25,
    "gn:feature_class":"P",
    "gn:feature_code":"PPL",
    "gn:name":"Bonto",
    "gn:population":0,
    "gn:timezone":"Africa/Banjul",
    "iso:country":"GM",
    "name:ceb_x_preferred":[
        "Bouto"
    ],
    "name:fra_x_preferred":[
        "Bouto"
    ],
    "wof:name":"Bonto",
    "wof:placetype":"locality"
},
  "geometry": {"coordinates":[-16.55944,13.27806],"type":"Point"}
}