{
  "type": "Feature",
  "properties": {
    "gn:admin1_code":"05",
    "gn:asciiname":"Sanchaba",
    "gn:country_code":"GM",
    "gn:dem":23,
    "gn:feature_class":"P",
    "gn:feature_code":"PPL",
    "gn:name":"Sanchaba",
    "gn:population":0,
    "gn:timezone":"Africa/Banjul",
    "iso:country":"GM",
    "wof:name":"Sanchaba",
    "wof:placetype":"locality"
},
  "geometry": {"coordinates":[-16.70972,13.42222],"type":"Point"}
}