{
  "type": "Feature",
  "properties": {
    "gn:admin1_code":"07",
    "gn:asciiname":"Medina Manneh",
    "gn:country_code":"GM",
    "gn:dem":41,
    "gn:feature_class":"P",
    "gn:feature_code":"PPL",
    "gn:name":"Medina Manneh",
    "gn:population":0,
    "gn:timezone":"Africa/Banjul",
    "iso:country":"GM",
    "wof:name":"Medina Manneh",
    "wof:placetype":"locality"
},
  "geometry": {"coordinates":[-16.39444,13.55861],"type":"Point"}
}