{
  "type": "Feature",
  "properties": {
    "gn:admin1_code":"03",
    "gn:asciiname":"Mbaien Wollof",
    "gn:country_code":"GM",
    "gn:dem":35,
    "gn:feature_class":"P",
    "gn:feature_code":"PPL",
    "gn:name":"Mbaien Wollof",
    "gn:population":0,
    "gn:timezone":"Africa/Banjul",
    "iso:country":"GM",
    "wof:name":"Mbaien Wollof",
    "wof:placetype":"locality"
},
  "geometry": {"coordinates":[-14.81667,13.73333],"type":"Point"}
}