{
  "type": "Feature",
  "properties": {
    "gn:admin1_code":"03",
    "gn:asciiname":"N'Jameng Kunda",
    "gn:country_code":"GM",
    "gn:dem":20,
    "gn:feature_class":"P",
    "gn:feature_code":"PPL",
    "gn:name":"N\u2019Jameng Kunda",
    "gn:population":0,
    "gn:timezone":"Africa/Banjul",
    "iso:country":"GM",
    "name:und_x_variant":[
        "N\u2019Jareng Kunda",
        "N\u2019Jameng Kunda"
    ],
    "wof:name":"N'Jameng Kunda",
    "wof:placetype":"locality"
},
  "geometry": {"coordinates":[-14.58333,13.43333],"type":"Point"}
}