{
  "type": "Feature",
  "properties": {
    "gn:admin1_code":"05",
    "gn:asciiname":"Kafenkeng",
    "gn:cc2":"GM",
    "gn:country_code":"GM",
    "gn:dem":35,
    "gn:feature_class":"P",
    "gn:feature_code":"PPL",
    "gn:name":"Kafenkeng",
    "gn:population":0,
    "gn:timezone":"Africa/Banjul",
    "iso:country":"GM",
    "name:und_x_variant":[
        "Kafenkena",
        "Kafenkeng"
    ],
    "wof:name":"Kafenkeng",
    "wof:placetype":"locality"
},
  "geometry": {"coordinates":[-16.00222,13.17167],"type":"Point"}
}