{
  "type": "Feature",
  "properties": {
    "gn:admin1_code":"04",
    "gn:asciiname":"Tia",
    "gn:country_code":"GM",
    "gn:dem":7,
    "gn:feature_class":"P",
    "gn:feature_code":"PPL",
    "gn:name":"Tia",
    "gn:population":0,
    "gn:timezone":"Africa/Banjul",
    "iso:country":"GM",
    "wof:name":"Tia",
    "wof:placetype":"locality"
},
  "geometry": {"coordinates":[-14.48333,13.38333],"type":"Point"}
}