{
  "type": "Feature",
  "properties": {
    "gn:admin1_code":"04",
    "gn:asciiname":"Alohungari",
    "gn:country_code":"GM",
    "gn:dem":21,
    "gn:feature_class":"P",
    "gn:feature_code":"PPL",
    "gn:name":"Alohungari",
    "gn:population":0,
    "gn:timezone":"Africa/Banjul",
    "iso:country":"GM",
    "wof:name":"Alohungari",
    "wof:placetype":"locality"
},
  "geometry": {"coordinates":[-14.23333,13.31667],"type":"Point"}
}