{
  "type": "Feature",
  "properties": {
    "gn:admin1_code":"03",
    "gn:asciiname":"Jafai",
    "gn:country_code":"GM",
    "gn:dem":16,
    "gn:feature_class":"P",
    "gn:feature_code":"PPL",
    "gn:name":"Jafai",
    "gn:population":0,
    "gn:timezone":"Africa/Banjul",
    "iso:country":"GM",
    "wof:name":"Jafai",
    "wof:placetype":"locality"
},
  "geometry": {"coordinates":[-15.08333,13.66667],"type":"Point"}
}