{
  "type": "Feature",
  "properties": {
    "gn:admin1_code":"04",
    "gn:asciiname":"Kristi Kunda",
    "gn:country_code":"GM",
    "gn:dem":25,
    "gn:feature_class":"P",
    "gn:feature_code":"PPL",
    "gn:name":"Kristi Kunda",
    "gn:population":0,
    "gn:timezone":"Africa/Banjul",
    "iso:country":"GM",
    "wof:name":"Kristi Kunda",
    "wof:placetype":"locality"
},
  "geometry": {"coordinates":[-13.86667,13.41667],"type":"Point"}
}