{
  "type": "Feature",
  "properties": {
    "gn:admin1_code":"05",
    "gn:asciiname":"Bulok",
    "gn:country_code":"GM",
    "gn:dem":23,
    "gn:feature_class":"P",
    "gn:feature_code":"PPL",
    "gn:name":"Bulok",
    "gn:population":0,
    "gn:timezone":"Africa/Banjul",
    "iso:country":"GM",
    "wof:name":"Bulok",
    "wof:placetype":"locality"
},
  "geometry": {"coordinates":[-16.41583,13.17667],"type":"Point"}
}