{
  "type": "Feature",
  "properties": {
    "gn:admin1_code":"03",
    "gn:asciiname":"Hamdalai",
    "gn:country_code":"GM",
    "gn:dem":27,
    "gn:feature_class":"P",
    "gn:feature_code":"PPL",
    "gn:name":"Hamdalai",
    "gn:population":0,
    "gn:timezone":"Africa/Banjul",
    "iso:country":"GM",
    "wof:name":"Hamdalai",
    "wof:placetype":"locality"
},
  "geometry": {"coordinates":[-15.15,13.58333],"type":"Point"}
}