{
  "type": "Feature",
  "properties": {
    "gn:country":"GM",
    "gn:fcode":"PPL",
    "gn:pop":378,
    "iso:country":"GM",
    "qs:name":"Jockul",
    "qs:photos_9r":0,
    "qs:photos_sr":0,
    "qs:pop_sr":"2",
    "wof:name":"Jockul",
    "wof:placetype":"locality",
    "wof:population":378
},
  "geometry": {"coordinates":[-15.16667,13.61667],"type":"Point"}
}