{
  "type": "Feature",
  "properties": {
    "gn:admin1_code":"05",
    "gn:asciiname":"Kiti Manjago",
    "gn:country_code":"GM",
    "gn:dem":25,
    "gn:feature_class":"P",
    "gn:feature_code":"PPL",
    "gn:name":"Kiti Manjago",
    "gn:population":0,
    "gn:timezone":"Africa/Banjul",
    "iso:country":"GM",
    "wof:name":"Kiti Manjago",
    "wof:placetype":"locality"
},
  "geometry": {"coordinates":[-16.66556,13.24611],"type":"Point"}
}