{
  "type": "Feature",
  "properties": {
    "gn:admin1_code":"07",
    "gn:asciiname":"Toro Tayem",
    "gn:cc2":"GM",
    "gn:country_code":"GM",
    "gn:dem":33,
    "gn:feature_class":"P",
    "gn:feature_code":"PPL",
    "gn:name":"Toro Tayem",
    "gn:population":0,
    "gn:timezone":"Africa/Banjul",
    "iso:country":"GM",
    "name:und_x_variant":[
        "N\u2019Toro Taim",
        "N\u2019Toro Tem",
        "Toro Tayem"
    ],
    "wof:name":"Toro Tayem",
    "wof:placetype":"locality"
},
  "geometry": {"coordinates":[-16.04833,13.56167],"type":"Point"}
}