{
  "type": "Feature",
  "properties": {
    "gn:admin1_code":"05",
    "gn:asciiname":"Tabo Kotor",
    "gn:cc2":"GM",
    "gn:country_code":"GM",
    "gn:dem":23,
    "gn:feature_class":"P",
    "gn:feature_code":"PPL",
    "gn:name":"Tabo Kotor",
    "gn:population":0,
    "gn:timezone":"Africa/Banjul",
    "iso:country":"GM",
    "name:und_x_variant":[
        "Tabokoto",
        "Tabo Kotor"
    ],
    "wof:name":"Tabo Kotor",
    "wof:placetype":"locality"
},
  "geometry": {"coordinates":[-16.66722,13.4075],"type":"Point"}
}