{
  "type": "Feature",
  "properties": {
    "gn:admin1_code":"04",
    "gn:asciiname":"Gillangel",
    "gn:country_code":"GM",
    "gn:dem":16,
    "gn:feature_class":"P",
    "gn:feature_code":"PPL",
    "gn:name":"Gillangel",
    "gn:population":0,
    "gn:timezone":"Africa/Banjul",
    "iso:country":"GM",
    "wof:name":"Gillangel",
    "wof:placetype":"locality"
},
  "geometry": {"coordinates":[-14.45,13.33333],"type":"Point"}
}