{
  "type": "Feature",
  "properties": {
    "gn:country":"GM",
    "gn:fcode":"PPL",
    "gn:population":158,
    "iso:country":"GM",
    "qs:name":"Temanto",
    "qs:photos_9r":0,
    "qs:photos_sr":0,
    "qs:pop_sr":"1",
    "wof:name":"Temanto",
    "wof:placetype":"locality",
    "wof:population":158
},
  "geometry": {"coordinates":[-13.91667,13.38333],"type":"Point"}
}