{
  "type": "Feature",
  "properties": {
    "gn:admin1_code":"04",
    "gn:asciiname":"Bankuwule",
    "gn:country_code":"GM",
    "gn:dem":36,
    "gn:feature_class":"P",
    "gn:feature_code":"PPL",
    "gn:name":"Bankuwule",
    "gn:population":0,
    "gn:timezone":"Africa/Banjul",
    "iso:country":"GM",
    "wof:name":"Bankuwule",
    "wof:placetype":"locality"
},
  "geometry": {"coordinates":[-14.13333,13.48333],"type":"Point"}
}