{
  "type": "Feature",
  "properties": {
    "gn:admin1_code":"07",
    "gn:asciiname":"Sika Baduma",
    "gn:country_code":"GM",
    "gn:dem":7,
    "gn:feature_class":"P",
    "gn:feature_code":"PPL",
    "gn:name":"Sika Baduma",
    "gn:population":0,
    "gn:timezone":"Africa/Banjul",
    "iso:country":"GM",
    "name:und_x_variant":[
        "Yolof",
        "Sika Baduma"
    ],
    "wof:name":"Sika Baduma",
    "wof:placetype":"locality"
},
  "geometry": {"coordinates":[-16.33833,13.35],"type":"Point"}
}