{
  "type": "Feature",
  "properties": {
    "gn:country":"GM",
    "gn:fcode":"PPL",
    "gn:pop":249,
    "iso:country":"GM",
    "qs:name":"Darusalam",
    "qs:photos_9r":0,
    "qs:photos_sr":0,
    "qs:pop_sr":"2",
    "wof:name":"Darusalam",
    "wof:placetype":"locality",
    "wof:population":249
},
  "geometry": {"coordinates":[-16.08083,13.52778],"type":"Point"}
}