{
  "type": "Feature",
  "properties": {
    "gn:admin1_code":"07",
    "gn:asciiname":"Kanuma",
    "gn:country_code":"GM",
    "gn:dem":9,
    "gn:feature_class":"P",
    "gn:feature_code":"PPL",
    "gn:name":"Kanuma",
    "gn:population":0,
    "gn:timezone":"Africa/Banjul",
    "iso:country":"GM",
    "wof:name":"Kanuma",
    "wof:placetype":"locality"
},
  "geometry": {"coordinates":[-16.50889,13.49917],"type":"Point"}
}