{
  "type": "Feature",
  "properties": {
    "gn:admin1_code":"03",
    "gn:asciiname":"Madina Njaine",
    "gn:country_code":"GM",
    "gn:dem":50,
    "gn:feature_class":"P",
    "gn:feature_code":"PPL",
    "gn:name":"Madina Njaine",
    "gn:population":0,
    "gn:timezone":"Africa/Banjul",
    "iso:country":"GM",
    "name:und_x_variant":[
        "Madina N\u2019Jaien",
        "Madina Njaine"
    ],
    "wof:name":"Madina Njaine",
    "wof:placetype":"locality"
},
  "geometry": {"coordinates":[-14.88333,13.75],"type":"Point"}
}