{
  "type": "Feature",
  "properties": {
    "gn:country":"GM",
    "gn:fcode":"PPL",
    "gn:population":385,
    "iso:country":"GM",
    "name:und_x_variant":[
        "Demfai"
    ],
    "qs:name":"Demfai Njaga",
    "qs:photos_9r":0,
    "qs:photos_sr":0,
    "qs:pop_sr":"2",
    "wof:name":"Demfai Njaga",
    "wof:placetype":"locality",
    "wof:population":385
},
  "geometry": {"coordinates":[-14.65,13.61667],"type":"Point"}
}