{
  "type": "Feature",
  "properties": {
    "gn:admin1_code":"04",
    "gn:asciiname":"Changally Lankadi",
    "gn:country_code":"GM",
    "gn:dem":25,
    "gn:feature_class":"P",
    "gn:feature_code":"PPL",
    "gn:name":"Changally Lankadi",
    "gn:population":0,
    "gn:timezone":"Africa/Banjul",
    "iso:country":"GM",
    "name:und_x_variant":[
        "Changally",
        "Changally Lankadi"
    ],
    "wof:name":"Changally Lankadi",
    "wof:placetype":"locality"
},
  "geometry": {"coordinates":[-14.33333,13.35],"type":"Point"}
}