{
  "type": "Feature",
  "properties": {
    "gn:admin1_code":"05",
    "gn:asciiname":"Sangajor Jiramba",
    "gn:country_code":"GM",
    "gn:dem":11,
    "gn:feature_class":"P",
    "gn:feature_code":"PPL",
    "gn:name":"Sangajor Jiramba",
    "gn:population":0,
    "gn:timezone":"Africa/Banjul",
    "iso:country":"GM",
    "wof:name":"Sangajor Jiramba",
    "wof:placetype":"locality"
},
  "geometry": {"coordinates":[-16.01806,13.26306],"type":"Point"}
}