{
  "type": "Feature",
  "properties": {
    "gn:admin1_code":"03",
    "gn:asciiname":"Madina Jawbeh",
    "gn:country_code":"GM",
    "gn:dem":9,
    "gn:feature_class":"P",
    "gn:feature_code":"PPL",
    "gn:name":"Madina Jawbeh",
    "gn:population":0,
    "gn:timezone":"Africa/Banjul",
    "iso:country":"GM",
    "wof:name":"Madina Jawbeh",
    "wof:placetype":"locality"
},
  "geometry": {"coordinates":[-14.86667,13.48333],"type":"Point"}
}