{
  "type": "Feature",
  "properties": {
    "gn:admin1_code":"04",
    "gn:asciiname":"Sare Wonku",
    "gn:country_code":"GM",
    "gn:dem":37,
    "gn:feature_class":"P",
    "gn:feature_code":"PPL",
    "gn:name":"Sare Wonku",
    "gn:population":0,
    "gn:timezone":"Africa/Banjul",
    "iso:country":"GM",
    "name:und_x_variant":[
        "Kuonko",
        "Sare Wonku"
    ],
    "wof:name":"Sare Wonku",
    "wof:placetype":"locality"
},
  "geometry": {"coordinates":[-14.31667,13.41667],"type":"Point"}
}