{
  "type": "Feature",
  "properties": {
    "gn:admin1_code":"05",
    "gn:asciiname":"Tubakuta",
    "gn:country_code":"GM",
    "gn:dem":31,
    "gn:feature_class":"P",
    "gn:feature_code":"PPL",
    "gn:name":"Tubakuta",
    "gn:population":0,
    "gn:timezone":"Africa/Banjul",
    "iso:country":"GM",
    "wof:name":"Tubakuta",
    "wof:placetype":"locality"
},
  "geometry": {"coordinates":[-16.28333,13.25],"type":"Point"}
}