{
  "type": "Feature",
  "properties": {
    "gn:country":"GM",
    "gn:fcode":"PPL",
    "gn:pop":1344,
    "iso:country":"GM",
    "qs:name":"Si Kunda",
    "qs:photos_9r":0,
    "qs:photos_sr":0,
    "qs:pop_sr":"3",
    "wof:name":"Si Kunda",
    "wof:placetype":"locality",
    "wof:population":1344
},
  "geometry": {"coordinates":[-15.56667,13.43333],"type":"Point"}
}