{
  "type": "Feature",
  "properties": {
    "gn:admin1_code":"04",
    "gn:asciiname":"Sinsu Demba",
    "gn:country_code":"GM",
    "gn:dem":40,
    "gn:feature_class":"P",
    "gn:feature_code":"PPL",
    "gn:name":"Sinsu Demba",
    "gn:population":0,
    "gn:timezone":"Africa/Banjul",
    "iso:country":"GM",
    "wof:name":"Sinsu Demba",
    "wof:placetype":"locality"
},
  "geometry": {"coordinates":[-14.33333,13.36667],"type":"Point"}
}