{
  "type": "Feature",
  "properties": {
    "gn:admin1_code":"03",
    "gn:asciiname":"Sare Jideh",
    "gn:country_code":"GM",
    "gn:dem":10,
    "gn:feature_class":"P",
    "gn:feature_code":"PPL",
    "gn:name":"Sare Jideh",
    "gn:population":0,
    "gn:timezone":"Africa/Banjul",
    "iso:country":"GM",
    "wof:name":"Sare Jideh",
    "wof:placetype":"locality"
},
  "geometry": {"coordinates":[-14.71667,13.55],"type":"Point"}
}