{
  "type": "Feature",
  "properties": {
    "gn:admin1_code":"05",
    "gn:asciiname":"Ndemban Ba",
    "gn:country_code":"GM",
    "gn:dem":14,
    "gn:feature_class":"P",
    "gn:feature_code":"PPL",
    "gn:name":"Ndemban Ba",
    "gn:population":0,
    "gn:timezone":"Africa/Banjul",
    "iso:country":"GM",
    "name:und_x_variant":[
        "Demban",
        "N\u2019Demban",
        "Kaie",
        "Ndemban Ba"
    ],
    "wof:name":"Ndemban Ba",
    "wof:placetype":"locality"
},
  "geometry": {"coordinates":[-16.34528,13.20778],"type":"Point"}
}