{
  "type": "Feature",
  "properties": {
    "gn:admin1_code":"05",
    "gn:asciiname":"Beeta Bukafungi",
    "gn:country_code":"GM",
    "gn:dem":28,
    "gn:feature_class":"P",
    "gn:feature_code":"PPL",
    "gn:name":"Beeta Bukafungi",
    "gn:population":0,
    "gn:timezone":"Africa/Banjul",
    "iso:country":"GM",
    "name:und_x_variant":[
        "Beeta",
        "Bita",
        "Beeta Bukafungi"
    ],
    "wof:name":"Beeta Bukafungi",
    "wof:placetype":"locality"
},
  "geometry": {"coordinates":[-16.2875,13.19056],"type":"Point"}
}