{
  "type": "Feature",
  "properties": {
    "gn:admin1_code":"04",
    "gn:asciiname":"Talito Musa",
    "gn:country_code":"GM",
    "gn:dem":38,
    "gn:feature_class":"P",
    "gn:feature_code":"PPL",
    "gn:name":"Talito Musa",
    "gn:population":0,
    "gn:timezone":"Africa/Banjul",
    "iso:country":"GM",
    "name:und_x_variant":[
        "Talito",
        "Talito Musa"
    ],
    "wof:name":"Talito Musa",
    "wof:placetype":"locality"
},
  "geometry": {"coordinates":[-14.28333,13.28333],"type":"Point"}
}