{
  "type": "Feature",
  "properties": {
    "gn:country":"GM",
    "gn:fcode":"PPL",
    "gn:population":186,
    "iso:country":"GM",
    "qs:name":"Sare Dadi",
    "qs:photos_9r":0,
    "qs:photos_sr":0,
    "qs:pop_sr":"1",
    "wof:name":"Sare Dadi",
    "wof:placetype":"locality",
    "wof:population":186
},
  "geometry": {"coordinates":[-14.68333,13.35],"type":"Point"}
}