{
  "type": "Feature",
  "properties": {
    "gn:admin1_code":"04",
    "gn:asciiname":"Sare Juley",
    "gn:country_code":"GM",
    "gn:dem":51,
    "gn:feature_class":"P",
    "gn:feature_code":"PPL",
    "gn:name":"Sare Juley",
    "gn:population":0,
    "gn:timezone":"Africa/Banjul",
    "iso:country":"GM",
    "name:und_x_variant":[
        "Darsilame",
        "Sare Juley"
    ],
    "wof:name":"Sare Juley",
    "wof:placetype":"locality"
},
  "geometry": {"coordinates":[-14.06667,13.33333],"type":"Point"}
}