{
  "type": "Feature",
  "properties": {
    "gn:admin1_code":"05",
    "gn:asciiname":"Santangba",
    "gn:country_code":"GM",
    "gn:dem":14,
    "gn:feature_class":"P",
    "gn:feature_code":"PPL",
    "gn:name":"Santangba",
    "gn:population":0,
    "gn:timezone":"Africa/Banjul",
    "iso:country":"GM",
    "wof:name":"Santangba",
    "wof:placetype":"locality"
},
  "geometry": {"coordinates":[-16.12611,13.24194],"type":"Point"}
}