{
  "type": "Feature",
  "properties": {
    "gn:admin1_code":"05",
    "gn:asciiname":"Sanyang",
    "gn:cc2":"GM",
    "gn:country_code":"GM",
    "gn:dem":22,
    "gn:feature_class":"P",
    "gn:feature_code":"PPL",
    "gn:name":"Sanyang",
    "gn:population":0,
    "gn:timezone":"Africa/Banjul",
    "iso:country":"GM",
    "name:ceb_x_preferred":[
        "Sanyang"
    ],
    "name:deu_x_preferred":[
        "Sanyang"
    ],
    "name:swe_x_preferred":[
        "Sanyang"
    ],
    "name:und_x_variant":[
        "Saniang"
    ],
    "wof:name":"Sanyang",
    "wof:placetype":"locality"
},
  "geometry": {"coordinates":[-16.76056,13.26667],"type":"Point"}
}