{
  "type": "Feature",
  "properties": {
    "gn:admin1_code":"04",
    "gn:asciiname":"Sare Belali",
    "gn:country_code":"GM",
    "gn:dem":49,
    "gn:feature_class":"P",
    "gn:feature_code":"PPL",
    "gn:name":"Sare Belali",
    "gn:population":0,
    "gn:timezone":"Africa/Banjul",
    "iso:country":"GM",
    "wof:name":"Sare Belali",
    "wof:placetype":"locality"
},
  "geometry": {"coordinates":[-14.16667,13.51667],"type":"Point"}
}