{
  "type": "Feature",
  "properties": {
    "gn:admin1_code":"07",
    "gn:asciiname":"Lang Sarr",
    "gn:country_code":"GM",
    "gn:dem":32,
    "gn:feature_class":"P",
    "gn:feature_code":"PPL",
    "gn:name":"Lang Sarr",
    "gn:population":0,
    "gn:timezone":"Africa/Banjul",
    "iso:country":"GM",
    "wof:name":"Lang Sarr",
    "wof:placetype":"locality"
},
  "geometry": {"coordinates":[-16.3625,13.57611],"type":"Point"}
}