{
  "type": "Feature",
  "properties": {
    "gn:admin1_code":"05",
    "gn:asciiname":"Busumbala",
    "gn:cc2":"GM",
    "gn:country_code":"GM",
    "gn:dem":27,
    "gn:feature_class":"P",
    "gn:feature_code":"PPL",
    "gn:name":"Busumbala",
    "gn:population":0,
    "gn:timezone":"Africa/Banjul",
    "iso:country":"GM",
    "name:und_x_variant":[
        "Busumbata",
        "Busumbala"
    ],
    "wof:name":"Busumbala",
    "wof:placetype":"locality"
},
  "geometry": {"coordinates":[-16.67083,13.33306],"type":"Point"}
}