{
  "type": "Feature",
  "properties": {
    "gn:admin1_code":"05",
    "gn:asciiname":"Sitta",
    "gn:cc2":"GM",
    "gn:country_code":"GM",
    "gn:dem":21,
    "gn:feature_class":"P",
    "gn:feature_code":"PPL",
    "gn:name":"Sitta",
    "gn:population":0,
    "gn:timezone":"Africa/Banjul",
    "iso:country":"GM",
    "name:und_x_variant":[
        "Sita",
        "Sitta"
    ],
    "wof:name":"Sitta",
    "wof:placetype":"locality"
},
  "geometry": {"coordinates":[-16.16222,13.23361],"type":"Point"}
}