{
  "type": "Feature",
  "properties": {
    "gn:admin1_code":"03",
    "gn:asciiname":"Balanghar Ker N'Derry",
    "gn:country_code":"GM",
    "gn:dem":18,
    "gn:feature_class":"P",
    "gn:feature_code":"PPL",
    "gn:name":"Balanghar Ker N\u2019Derry",
    "gn:population":0,
    "gn:timezone":"Africa/Banjul",
    "iso:country":"GM",
    "name:und_x_variant":[
        "Balangar",
        "Ballangar",
        "Balanghar Ker N\u2019Derry"
    ],
    "wof:name":"Balanghar Ker N'Derry",
    "wof:placetype":"locality"
},
  "geometry": {"coordinates":[-15.39936,13.66411],"type":"Point"}
}