{
  "type": "Feature",
  "properties": {
    "gn:admin1_code":"02",
    "gn:asciiname":"Sare Fonkoi",
    "gn:country_code":"GM",
    "gn:dem":38,
    "gn:feature_class":"P",
    "gn:feature_code":"PPL",
    "gn:name":"Sare Fonkoi",
    "gn:population":0,
    "gn:timezone":"Africa/Banjul",
    "iso:country":"GM",
    "wof:name":"Sare Fonkoi",
    "wof:placetype":"locality"
},
  "geometry": {"coordinates":[-15.56667,13.38333],"type":"Point"}
}