{
  "type": "Feature",
  "properties": {
    "gn:country":"GM",
    "gn:fcode":"PPL",
    "gn:population":80,
    "iso:country":"GM",
    "qs:name":"Toben",
    "qs:photos_9r":0,
    "qs:photos_sr":0,
    "qs:pop_sr":"1",
    "wof:name":"Toben",
    "wof:placetype":"locality",
    "wof:population":80
},
  "geometry": {"coordinates":[-14.85,13.75],"type":"Point"}
}