{
  "type": "Feature",
  "properties": {
    "gn:admin1_code":"04",
    "gn:asciiname":"Bajankoto",
    "gn:country_code":"GM",
    "gn:dem":15,
    "gn:feature_class":"P",
    "gn:feature_code":"PPL",
    "gn:name":"Bajankoto",
    "gn:population":0,
    "gn:timezone":"Africa/Banjul",
    "iso:country":"GM",
    "name:und_x_variant":[
        "Perai Memadi",
        "Bajankoto"
    ],
    "wof:name":"Bajankoto",
    "wof:placetype":"locality"
},
  "geometry": {"coordinates":[-14.25,13.38333],"type":"Point"}
}