{
  "type": "Feature",
  "properties": {
    "gn:admin1_code":"05",
    "gn:asciiname":"Kanjending",
    "gn:country_code":"GM",
    "gn:dem":27,
    "gn:feature_class":"P",
    "gn:feature_code":"PPL",
    "gn:name":"Kanjending",
    "gn:population":0,
    "gn:timezone":"Africa/Banjul",
    "iso:country":"GM",
    "wof:name":"Kanjending",
    "wof:placetype":"locality"
},
  "geometry": {"coordinates":[-15.96667,13.23333],"type":"Point"}
}