{
  "type": "Feature",
  "properties": {
    "gn:country":"GM",
    "gn:fcode":"PPL",
    "gn:pop":184,
    "iso:country":"GM",
    "qs:name":"Sare Malang",
    "qs:photos_9r":0,
    "qs:photos_sr":0,
    "qs:pop_sr":"1",
    "wof:name":"Sare Malang",
    "wof:placetype":"locality",
    "wof:population":184
},
  "geometry": {"coordinates":[-15.01667,13.55],"type":"Point"}
}