{
  "type": "Feature",
  "properties": {
    "gn:country":"GM",
    "gn:fcode":"PPL",
    "gn:population":301,
    "iso:country":"GM",
    "name:ben_x_preferred":[
        "\u09a8\u09c7\u09ae\u09be"
    ],
    "name:ceb_x_preferred":[
        "Nema"
    ],
    "name:epo_x_preferred":[
        "Nema"
    ],
    "name:fra_x_preferred":[
        "Nema"
    ],
    "name:hin_x_preferred":[
        "\u0928\u0947\u092e\u093e"
    ],
    "name:ita_x_preferred":[
        "Nema"
    ],
    "name:swe_x_preferred":[
        "Nema"
    ],
    "name:tur_x_preferred":[
        "Nema"
    ],
    "qs:name":"Nema",
    "qs:photos_9r":0,
    "qs:photos_sr":0,
    "qs:pop_sr":"2",
    "wof:name":"Nema",
    "wof:placetype":"locality",
    "wof:population":301
},
  "geometry": {"coordinates":[-14.81667,13.53333],"type":"Point"}
}