{
  "type": "Feature",
  "properties": {
    "gn:country":"GM",
    "gn:fcode":"PPL",
    "gn:pop":301,
    "iso:country":"GM",
    "qs:name":"Nema",
    "qs:photos_9r":0,
    "qs:photos_sr":0,
    "qs:pop_sr":"2",
    "wof:name":"Nema",
    "wof:placetype":"locality",
    "wof:population":301
},
  "geometry": {"coordinates":[-14.81667,13.53333],"type":"Point"}
}