{
  "type": "Feature",
  "properties": {
    "gn:admin1_code":"05",
    "gn:asciiname":"Kamessing",
    "gn:country_code":"GM",
    "gn:dem":39,
    "gn:feature_class":"P",
    "gn:feature_code":"PPL",
    "gn:name":"Kamessing",
    "gn:population":0,
    "gn:timezone":"Africa/Banjul",
    "iso:country":"GM",
    "wof:name":"Kamessing",
    "wof:placetype":"locality"
},
  "geometry": {"coordinates":[-15.83333,13.18333],"type":"Point"}
}