{
  "type": "Feature",
  "properties": {
    "gn:admin1_code":"05",
    "gn:asciiname":"Kambagol",
    "gn:cc2":"GM",
    "gn:country_code":"GM",
    "gn:dem":42,
    "gn:feature_class":"P",
    "gn:feature_code":"PPL",
    "gn:name":"Kambagol",
    "gn:population":0,
    "gn:timezone":"Africa/Banjul",
    "iso:country":"GM",
    "name:und_x_variant":[
        "Kambagali",
        "Kambagol"
    ],
    "wof:name":"Kambagol",
    "wof:placetype":"locality"
},
  "geometry": {"coordinates":[-16.08222,13.18472],"type":"Point"}
}