{
  "type": "Feature",
  "properties": {
    "gn:admin1_code":"07",
    "gn:asciiname":"Jebbel Satou",
    "gn:country_code":"GM",
    "gn:dem":23,
    "gn:feature_class":"P",
    "gn:feature_code":"PPL",
    "gn:name":"Jebbel Satou",
    "gn:population":39,
    "gn:timezone":"Africa/Banjul",
    "iso:country":"GM",
    "wof:name":"Jebbel Satou",
    "wof:placetype":"locality",
    "wof:population":39
},
  "geometry": {"coordinates":[-16.04854,13.58926],"type":"Point"}
}