{
  "type": "Feature",
  "properties": {
    "gn:admin1_code":"04",
    "gn:asciiname":"Demba Kumbale",
    "gn:country_code":"GM",
    "gn:dem":46,
    "gn:feature_class":"P",
    "gn:feature_code":"PPL",
    "gn:name":"Demba Kumbale",
    "gn:population":0,
    "gn:timezone":"Africa/Banjul",
    "iso:country":"GM",
    "name:und_x_variant":[
        "Dembo Kumbel",
        "Demba Koumbel",
        "Demba Kumbale"
    ],
    "wof:name":"Demba Kumbale",
    "wof:placetype":"locality"
},
  "geometry": {"coordinates":[-13.85,13.46667],"type":"Point"}
}