{
  "type": "Feature",
  "properties": {
    "gn:country":"GM",
    "gn:fcode":"PPL",
    "gn:pop":370,
    "iso:country":"GM",
    "qs:name":"Kekuta Kunda",
    "qs:photos_9r":0,
    "qs:photos_sr":0,
    "qs:pop_sr":"2",
    "wof:name":"Kekuta Kunda",
    "wof:placetype":"locality",
    "wof:population":370
},
  "geometry": {"coordinates":[-15.85,13.56667],"type":"Point"}
}