{
  "type": "Feature",
  "properties": {
    "iso:country":"GM",
    "name:unk_x_variant":[
        "Jeswang"
    ],
    "qs:gn_country":"GM",
    "qs:gn_fcode":"PPL",
    "qs:gn_pop":0,
    "qs:name":"Sere Kunda",
    "qs:name_adm0":"The Gambia",
    "qs:name_adm1":"Western",
    "qs:photos":1218,
    "qs:photos_1k":247,
    "qs:photos_9k":5,
    "qs:photos_9r":7,
    "qs:photos_all":1218,
    "qs:photos_sr":11,
    "qs:placetype":"Town",
    "qs:pop_sr":"0",
    "qs:woe_adm0":23424821,
    "wof:name":"Sere Kunda",
    "wof:placetype":"locality"
},
  "geometry": {"coordinates":[-16.68139,13.4425],"type":"Point"}
}