{
  "type": "Feature",
  "properties": {
    "gn:admin1_code":"07",
    "gn:asciiname":"Mbulum",
    "gn:country_code":"GM",
    "gn:dem":40,
    "gn:feature_class":"P",
    "gn:feature_code":"PPL",
    "gn:name":"Mbulum",
    "gn:population":0,
    "gn:timezone":"Africa/Banjul",
    "iso:country":"GM",
    "wof:name":"Mbulum",
    "wof:placetype":"locality"
},
  "geometry": {"coordinates":[-16.40667,13.53556],"type":"Point"}
}