{
  "type": "Feature",
  "properties": {
    "gn:admin1_code":"03",
    "gn:asciiname":"Sare Yoro",
    "gn:country_code":"GM",
    "gn:dem":22,
    "gn:feature_class":"P",
    "gn:feature_code":"PPL",
    "gn:name":"Sare Yoro",
    "gn:population":0,
    "gn:timezone":"Africa/Banjul",
    "iso:country":"GM",
    "name:und_x_variant":[
        "Sare Yoro Taker",
        "Sare Yoro Takor",
        "Sare Yoro"
    ],
    "wof:name":"Sare Yoro",
    "wof:placetype":"locality"
},
  "geometry": {"coordinates":[-14.86667,13.46667],"type":"Point"}
}