{
  "type": "Feature",
  "properties": {
    "gn:admin1_code":"05",
    "gn:asciiname":"Sare Jutah",
    "gn:country_code":"GM",
    "gn:dem":24,
    "gn:feature_class":"P",
    "gn:feature_code":"PPL",
    "gn:name":"Sare Jutah",
    "gn:population":0,
    "gn:timezone":"Africa/Banjul",
    "iso:country":"GM",
    "wof:name":"Sare Jutah",
    "wof:placetype":"locality"
},
  "geometry": {"coordinates":[-16.63332999999999,13.25],"type":"Point"}
}