{
  "type": "Feature",
  "properties": {
    "gn:admin1_code":"05",
    "gn:asciiname":"Dewru",
    "gn:country_code":"GM",
    "gn:dem":26,
    "gn:feature_class":"P",
    "gn:feature_code":"PPL",
    "gn:name":"Dewru",
    "gn:population":0,
    "gn:timezone":"Africa/Banjul",
    "iso:country":"GM",
    "wof:name":"Dewru",
    "wof:placetype":"locality"
},
  "geometry": {"coordinates":[-16.62778,13.26278],"type":"Point"}
}