{
  "type": "Feature",
  "properties": {
    "gn:admin1_code":"03",
    "gn:asciiname":"Janeh Kunda",
    "gn:country_code":"GM",
    "gn:dem":23,
    "gn:feature_class":"P",
    "gn:feature_code":"PPL",
    "gn:name":"Janeh Kunda",
    "gn:population":0,
    "gn:timezone":"Africa/Banjul",
    "iso:country":"GM",
    "wof:name":"Janeh Kunda",
    "wof:placetype":"locality"
},
  "geometry": {"coordinates":[-14.61667,13.65],"type":"Point"}
}