{
  "type": "Feature",
  "properties": {
    "gn:admin1_code":"03",
    "gn:asciiname":"Kuyarang",
    "gn:country_code":"GM",
    "gn:dem":3,
    "gn:feature_class":"P",
    "gn:feature_code":"PPL",
    "gn:name":"Kuyarang",
    "gn:population":0,
    "gn:timezone":"Africa/Banjul",
    "iso:country":"GM",
    "name:und_x_variant":[
        "Kuiran",
        "Kuyarang"
    ],
    "wof:name":"Kuyarang",
    "wof:placetype":"locality"
},
  "geometry": {"coordinates":[-14.83333,13.66667],"type":"Point"}
}