{
  "type": "Feature",
  "properties": {
    "gn:admin1_code":"07",
    "gn:asciiname":"Bali Hali Hawah",
    "gn:cc2":"GM",
    "gn:country_code":"GM",
    "gn:dem":17,
    "gn:feature_class":"P",
    "gn:feature_code":"PPL",
    "gn:name":"Bali Hali Hawah",
    "gn:population":0,
    "gn:timezone":"Africa/Banjul",
    "iso:country":"GM",
    "name:und_x_variant":[
        "Bali Hali Howeh",
        "Bali Hali Hawah"
    ],
    "wof:name":"Bali Hali Hawah",
    "wof:placetype":"locality"
},
  "geometry": {"coordinates":[-16.11167,13.59],"type":"Point"}
}