{
  "type": "Feature",
  "properties": {
    "gn:admin1_code":"07",
    "gn:asciiname":"Ker Biran Kani",
    "gn:country_code":"GM",
    "gn:dem":38,
    "gn:feature_class":"P",
    "gn:feature_code":"PPL",
    "gn:name":"Ker Biran Kani",
    "gn:population":0,
    "gn:timezone":"Africa/Banjul",
    "iso:country":"GM",
    "wof:name":"Ker Biran Kani",
    "wof:placetype":"locality"
},
  "geometry": {"coordinates":[-16.31806,13.495],"type":"Point"}
}