{
  "type": "Feature",
  "properties": {
    "gn:country":"GM",
    "gn:fcode":"PPL",
    "gn:population":251,
    "iso:country":"GM",
    "name:und_x_variant":[
        "Sinchu Kusalang"
    ],
    "qs:name":"Kusalang",
    "qs:photos_9r":0,
    "qs:photos_sr":0,
    "qs:pop_sr":"2",
    "wof:name":"Kusalang",
    "wof:placetype":"locality",
    "wof:population":251
},
  "geometry": {"coordinates":[-14.86667,13.45],"type":"Point"}
}