{
  "type": "Feature",
  "properties": {
    "gn:admin1_code":"05",
    "gn:asciiname":"Sukuta",
    "gn:country_code":"GM",
    "gn:dem":19,
    "gn:feature_class":"P",
    "gn:feature_code":"PPL",
    "gn:name":"Sukuta",
    "gn:population":0,
    "gn:timezone":"Africa/Banjul",
    "iso:country":"GM",
    "wof:name":"Sukuta",
    "wof:placetype":"locality"
},
  "geometry": {"coordinates":[-16.58333,13.18333],"type":"Point"}
}