{
  "type": "Feature",
  "properties": {
    "gn:admin1_code":"05",
    "gn:asciiname":"Sukuta",
    "gn:country_code":"GM",
    "gn:dem":19,
    "gn:feature_class":"P",
    "gn:feature_code":"PPL",
    "gn:name":"Sukuta",
    "gn:population":0,
    "gn:timezone":"Africa/Banjul",
    "iso:country":"GM",
    "name:ceb_x_preferred":[
        "Sukuta"
    ],
    "name:deu_x_preferred":[
        "Sukuta"
    ],
    "name:hun_x_preferred":[
        "Sukuta"
    ],
    "name:ita_x_preferred":[
        "Sukuta"
    ],
    "name:pol_x_preferred":[
        "Sukuta"
    ],
    "name:ron_x_preferred":[
        "Sukuta"
    ],
    "name:swe_x_preferred":[
        "Sukuta"
    ],
    "name:zho_x_preferred":[
        "\u8607\u5eab\u5854"
    ],
    "wof:name":"Sukuta",
    "wof:placetype":"locality"
},
  "geometry": {"coordinates":[-16.58333,13.18333],"type":"Point"}
}