{
  "type": "Feature",
  "properties": {
    "gn:admin1_code":"07",
    "gn:asciiname":"Ker Samba Yassin",
    "gn:country_code":"GM",
    "gn:dem":29,
    "gn:feature_class":"P",
    "gn:feature_code":"PPL",
    "gn:name":"Ker Samba Yassin",
    "gn:population":0,
    "gn:timezone":"Africa/Banjul",
    "iso:country":"GM",
    "wof:name":"Ker Samba Yassin",
    "wof:placetype":"locality"
},
  "geometry": {"coordinates":[-16.35361,13.59111],"type":"Point"}
}