{
  "type": "Feature",
  "properties": {
    "gn:admin1_code":"03",
    "gn:asciiname":"Jessadi Tenda",
    "gn:country_code":"GM",
    "gn:dem":5,
    "gn:feature_class":"P",
    "gn:feature_code":"PPL",
    "gn:name":"Jessadi Tenda",
    "gn:population":0,
    "gn:timezone":"Africa/Banjul",
    "iso:country":"GM",
    "name:und_x_variant":[
        "Jessida Tenda",
        "Jessadi Tenda"
    ],
    "wof:name":"Jessadi Tenda",
    "wof:placetype":"locality"
},
  "geometry": {"coordinates":[-15.26667,13.65],"type":"Point"}
}