{
  "type": "Feature",
  "properties": {
    "gn:admin1_code":"05",
    "gn:asciiname":"Sortokoi",
    "gn:cc2":"GM",
    "gn:country_code":"GM",
    "gn:dem":18,
    "gn:feature_class":"P",
    "gn:feature_code":"PPL",
    "gn:name":"Sortokoi",
    "gn:population":0,
    "gn:timezone":"Africa/Banjul",
    "iso:country":"GM",
    "name:und_x_variant":[
        "Sotokoi",
        "Sortokoi"
    ],
    "wof:name":"Sortokoi",
    "wof:placetype":"locality"
},
  "geometry": {"coordinates":[-16.74444,13.37056],"type":"Point"}
}