{
  "type": "Feature",
  "properties": {
    "gn:admin1_code":"07",
    "gn:asciiname":"Albadarr",
    "gn:country_code":"GM",
    "gn:dem":7,
    "gn:feature_class":"P",
    "gn:feature_code":"PPL",
    "gn:name":"Albadarr",
    "gn:population":0,
    "gn:timezone":"Africa/Banjul",
    "iso:country":"GM",
    "name:und_x_variant":[
        "Albreda",
        "Albadarr"
    ],
    "wof:name":"Albadarr",
    "wof:placetype":"locality"
},
  "geometry": {"coordinates":[-16.38667,13.33444],"type":"Point"}
}