{
  "type": "Feature",
  "properties": {
    "gn:country":"GM",
    "gn:fcode":"PPL",
    "gn:population":603,
    "iso:country":"GM",
    "qs:name":"Jeriko",
    "qs:photos_9r":0,
    "qs:photos_sr":0,
    "qs:pop_sr":"2",
    "wof:name":"Jeriko",
    "wof:placetype":"locality",
    "wof:population":603
},
  "geometry": {"coordinates":[-15.66667,13.58333],"type":"Point"}
}