{
  "type": "Feature",
  "properties": {
    "gn:admin1_code":"05",
    "gn:asciiname":"Kamemero",
    "gn:country_code":"GM",
    "gn:dem":35,
    "gn:feature_class":"P",
    "gn:feature_code":"PPL",
    "gn:name":"Kamemero",
    "gn:population":0,
    "gn:timezone":"Africa/Banjul",
    "iso:country":"GM",
    "name:und_x_variant":[
        "Kamenero",
        "Kamemero"
    ],
    "wof:name":"Kamemero",
    "wof:placetype":"locality"
},
  "geometry": {"coordinates":[-15.81667,13.21667],"type":"Point"}
}