{
  "type": "Feature",
  "properties": {
    "gn:admin1_code":"02",
    "gn:asciiname":"Sare Mamoudu",
    "gn:country_code":"GM",
    "gn:dem":36,
    "gn:feature_class":"P",
    "gn:feature_code":"PPL",
    "gn:name":"Sare Mamoudu",
    "gn:population":0,
    "gn:timezone":"Africa/Banjul",
    "iso:country":"GM",
    "name:und_x_variant":[
        "Sare Mamoudou",
        "Sare Mamoudu"
    ],
    "wof:name":"Sare Mamoudu",
    "wof:placetype":"locality"
},
  "geometry": {"coordinates":[-15.71667,13.36667],"type":"Point"}
}