{
  "type": "Feature",
  "properties": {
    "gn:admin1_code":"05",
    "gn:asciiname":"Sotokoi",
    "gn:country_code":"GM",
    "gn:dem":16,
    "gn:feature_class":"P",
    "gn:feature_code":"PPL",
    "gn:name":"Sotokoi",
    "gn:population":0,
    "gn:timezone":"Africa/Banjul",
    "iso:country":"GM",
    "wof:name":"Sotokoi",
    "wof:placetype":"locality"
},
  "geometry": {"coordinates":[-16.50472,13.22722],"type":"Point"}
}