{
  "type": "Feature",
  "properties": {
    "gn:country":"GM",
    "gn:fcode":"PPL",
    "gn:population":170,
    "iso:country":"GM",
    "qs:name":"Jiffet",
    "qs:photos_9r":0,
    "qs:photos_sr":0,
    "qs:pop_sr":"1",
    "wof:name":"Jiffet",
    "wof:placetype":"locality",
    "wof:population":170
},
  "geometry": {"coordinates":[-16.50139,13.48472],"type":"Point"}
}