{
  "type": "Feature",
  "properties": {
    "gn:admin1_code":"07",
    "gn:asciiname":"Mayamba",
    "gn:cc2":"GM",
    "gn:country_code":"GM",
    "gn:dem":14,
    "gn:feature_class":"P",
    "gn:feature_code":"PPL",
    "gn:name":"Mayamba",
    "gn:population":0,
    "gn:timezone":"Africa/Banjul",
    "iso:country":"GM",
    "name:und_x_variant":[
        "Myamba",
        "Mayamba"
    ],
    "wof:name":"Mayamba",
    "wof:placetype":"locality"
},
  "geometry": {"coordinates":[-16.51694,13.49417],"type":"Point"}
}