{
  "type": "Feature",
  "properties": {
    "gn:country":"GM",
    "gn:fcode":"PPL",
    "gn:population":59,
    "iso:country":"GM",
    "qs:name":"Konteh",
    "qs:photos_9r":0,
    "qs:photos_sr":0,
    "qs:pop_sr":"1",
    "wof:name":"Konteh",
    "wof:placetype":"locality",
    "wof:population":59
},
  "geometry": {"coordinates":[-15.16667,13.71667],"type":"Point"}
}