{
  "type": "Feature",
  "properties": {
    "gn:country":"GM",
    "gn:fcode":"PPL",
    "gn:population":173,
    "iso:country":"GM",
    "name:und_x_variant":[
        "Bumari"
    ],
    "qs:name":"Tabanani",
    "qs:photos_9r":0,
    "qs:photos_sr":0,
    "qs:pop_sr":"1",
    "wof:name":"Tabanani",
    "wof:placetype":"locality",
    "wof:population":173
},
  "geometry": {"coordinates":[-15.76667,13.36667],"type":"Point"}
}