{
  "type": "Feature",
  "properties": {
    "gn:admin1_code":"03",
    "gn:asciiname":"Brikama",
    "gn:country_code":"GM",
    "gn:dem":13,
    "gn:feature_class":"P",
    "gn:feature_code":"PPL",
    "gn:name":"Brikama",
    "gn:population":0,
    "gn:timezone":"Africa/Banjul",
    "iso:country":"GM",
    "wof:name":"Brikama",
    "wof:placetype":"locality"
},
  "geometry": {"coordinates":[-15.33333,13.56667],"type":"Point"}
}