{
  "type": "Feature",
  "properties": {
    "gn:admin1_code":"03",
    "gn:asciiname":"Brikama",
    "gn:country_code":"GM",
    "gn:dem":13,
    "gn:feature_class":"P",
    "gn:feature_code":"PPL",
    "gn:name":"Brikama",
    "gn:population":0,
    "gn:timezone":"Africa/Banjul",
    "iso:country":"GM",
    "name:bar_x_preferred":[
        "Brikama"
    ],
    "name:ben_x_preferred":[
        "\u09ac\u09cd\u09b0\u09bf\u0995\u09be\u09ae\u09be"
    ],
    "name:ceb_x_preferred":[
        "Brikama"
    ],
    "name:dan_x_preferred":[
        "Brikama"
    ],
    "name:deu_x_preferred":[
        "Brikama"
    ],
    "name:ell_x_preferred":[
        "\u039c\u03c0\u03c1\u03b9\u03ba\u03ac\u03bc\u03b1"
    ],
    "name:epo_x_preferred":[
        "Brikama"
    ],
    "name:est_x_preferred":[
        "Brikama"
    ],
    "name:fra_x_preferred":[
        "Brikama"
    ],
    "name:glg_x_preferred":[
        "Brikama"
    ],
    "name:hin_x_preferred":[
        "\u092c\u094d\u0930\u093f\u0915\u092e\u093e"
    ],
    "name:hun_x_preferred":[
        "Brikama"
    ],
    "name:ind_x_preferred":[
        "Brikama"
    ],
    "name:ita_x_preferred":[
        "Brikama"
    ],
    "name:jpn_x_preferred":[
        "\u30d6\u30ea\u30ab\u30de"
    ],
    "name:kat_x_preferred":[
        "\u10d1\u10e0\u10d8\u10d9\u10d0\u10db\u10d0"
    ],
    "name:kor_x_preferred":[
        "\ube0c\ub9ac\uce74\ub9c8"
    ],
    "name:lit_x_preferred":[
        "Brikama"
    ],
    "name:nld_x_preferred":[
        "Brikama"
    ],
    "name:nor_x_preferred":[
        "Brikama"
    ],
    "name:pol_x_preferred":[
        "Brikama"
    ],
    "name:por_x_preferred":[
        "Brikama"
    ],
    "name:ron_x_preferred":[
        "Brikama"
    ],
    "name:rus_x_preferred":[
        "\u0411\u0440\u0438\u043a\u0430\u043c\u0430"
    ],
    "name:spa_x_preferred":[
        "Brikama"
    ],
    "name:swe_x_preferred":[
        "Brikama"
    ],
    "name:tur_x_preferred":[
        "Brikama"
    ],
    "name:urd_x_preferred":[
        "\u0628\u0631\u06cc\u06a9\u0627\u0645\u0627"
    ],
    "name:vie_x_preferred":[
        "Brikama"
    ],
    "name:xmf_x_preferred":[
        "\u10d1\u10e0\u10d8\u10d9\u10d0\u10db\u10d0"
    ],
    "name:zho_x_preferred":[
        "\u5e03\u91cc\u5361\u99ac"
    ],
    "wof:name":"Brikama",
    "wof:placetype":"locality"
},
  "geometry": {"coordinates":[-15.33333,13.56667],"type":"Point"}
}