{
  "type": "Feature",
  "properties": {
    "gn:admin1_code":"03",
    "gn:asciiname":"Wellingara Galo",
    "gn:country_code":"GM",
    "gn:dem":46,
    "gn:feature_class":"P",
    "gn:feature_code":"PPL",
    "gn:name":"Wellingara Galo",
    "gn:population":0,
    "gn:timezone":"Africa/Banjul",
    "iso:country":"GM",
    "wof:name":"Wellingara Galo",
    "wof:placetype":"locality"
},
  "geometry": {"coordinates":[-14.78333,13.45],"type":"Point"}
}