{
  "type": "Feature",
  "properties": {
    "gn:admin1_code":"03",
    "gn:asciiname":"Sare Goral Bah",
    "gn:country_code":"GM",
    "gn:dem":31,
    "gn:feature_class":"P",
    "gn:feature_code":"PPL",
    "gn:name":"Sare Goral Bah",
    "gn:population":0,
    "gn:timezone":"Africa/Banjul",
    "iso:country":"GM",
    "wof:name":"Sare Goral Bah",
    "wof:placetype":"locality"
},
  "geometry": {"coordinates":[-14.58333,13.41667],"type":"Point"}
}