{
  "type": "Feature",
  "properties": {
    "iso:country":"GM",
    "name:ceb_x_preferred":[
        "Baro Kunda"
    ],
    "name:deu_x_preferred":[
        "Baro Kunda"
    ],
    "name:eng_x_preferred":[
        "Baro Kunda"
    ],
    "name:fas_x_preferred":[
        "\u0628\u0627\u0631\u0648 \u06a9\u0648\u0646\u062f\u0627"
    ],
    "name:nld_x_preferred":[
        "Baro Kunda"
    ],
    "name:swe_x_preferred":[
        "Baro Kunda"
    ],
    "name:und_x_variant":[
        "Barukunda"
    ],
    "qs:gn_country":"GM",
    "qs:gn_fcode":"PPL",
    "qs:gn_pop":1991,
    "qs:name":"Baro Kunda",
    "qs:name_adm0":"The Gambia",
    "qs:name_adm1":"Lower River",
    "qs:photos":0,
    "qs:photos_1k":0,
    "qs:photos_9k":1,
    "qs:photos_9r":1,
    "qs:photos_all":1,
    "qs:photos_sr":0,
    "qs:placetype":"Town",
    "qs:pop_sr":"3",
    "qs:woe_adm0":23424821,
    "wd:wordcount":42,
    "wof:name":"Baro Kunda",
    "wof:placetype":"locality",
    "wof:population":1991
},
  "geometry": {"coordinates":[-15.26667,13.48333],"type":"Point"}
}