{
  "type": "Feature",
  "properties": {
    "gn:admin1_code":"03",
    "gn:asciiname":"Tabaworo Kunda",
    "gn:country_code":"GM",
    "gn:dem":19,
    "gn:feature_class":"P",
    "gn:feature_code":"PPL",
    "gn:name":"Tabaworo Kunda",
    "gn:population":0,
    "gn:timezone":"Africa/Banjul",
    "iso:country":"GM",
    "wof:name":"Tabaworo Kunda",
    "wof:placetype":"locality"
},
  "geometry": {"coordinates":[-15.38333,13.66667],"type":"Point"}
}