{
  "type": "Feature",
  "properties": {
    "gn:admin1_code":"05",
    "gn:asciiname":"Kaffenkeng",
    "gn:country_code":"GM",
    "gn:dem":37,
    "gn:feature_class":"P",
    "gn:feature_code":"PPL",
    "gn:name":"Kaffenkeng",
    "gn:population":0,
    "gn:timezone":"Africa/Banjul",
    "iso:country":"GM",
    "wof:name":"Kaffenkeng",
    "wof:placetype":"locality"
},
  "geometry": {"coordinates":[-15.91667,13.18333],"type":"Point"}
}