{
  "type": "Feature",
  "properties": {
    "gn:admin1_code":"03",
    "gn:asciiname":"Gunkoru Wollof",
    "gn:country_code":"GM",
    "gn:dem":23,
    "gn:feature_class":"P",
    "gn:feature_code":"PPL",
    "gn:name":"Gunkoru Wollof",
    "gn:population":0,
    "gn:timezone":"Africa/Banjul",
    "iso:country":"GM",
    "name:und_x_variant":[
        "Gunkoru Wolloff",
        "Gunkeru",
        "Gunkoru Wollof"
    ],
    "wof:name":"Gunkoru Wollof",
    "wof:placetype":"locality"
},
  "geometry": {"coordinates":[-15.38333,13.71667],"type":"Point"}
}