{
  "type": "Feature",
  "properties": {
    "gn:country":"GM",
    "gn:fcode":"PPL",
    "gn:pop":78,
    "iso:country":"GM",
    "qs:name":"Yoro Ya",
    "qs:photos_9r":0,
    "qs:photos_sr":0,
    "qs:pop_sr":"1",
    "wof:name":"Yoro Ya",
    "wof:placetype":"locality",
    "wof:population":78
},
  "geometry": {"coordinates":[-15.28333,13.63333],"type":"Point"}
}