{
  "type": "Feature",
  "properties": {
    "gn:country":"GM",
    "gn:fcode":"PPL",
    "gn:population":185,
    "iso:country":"GM",
    "name:ceb_x_preferred":[
        "Demba Kunda"
    ],
    "name:deu_x_preferred":[
        "Demba Kunda"
    ],
    "name:eng_x_preferred":[
        "Demba Kunda"
    ],
    "name:fas_x_preferred":[
        "\u062f\u0645\u0628\u0627 \u06a9\u0648\u0646\u062f\u0627"
    ],
    "name:nld_x_preferred":[
        "Demba Kunda"
    ],
    "name:swe_x_preferred":[
        "Demba Kunda"
    ],
    "name:tur_x_preferred":[
        "Demba Kunda"
    ],
    "qs:name":"Demba Kunda",
    "qs:photos_9r":0,
    "qs:photos_sr":0,
    "qs:pop_sr":"1",
    "wd:wordcount":54,
    "wof:name":"Demba Kunda",
    "wof:placetype":"locality",
    "wof:population":185
},
  "geometry": {"coordinates":[-15.31667,13.55],"type":"Point"}
}