{
  "type": "Feature",
  "properties": {
    "gn:admin1_code":"07",
    "gn:asciiname":"Tiaba",
    "gn:country_code":"GM",
    "gn:dem":16,
    "gn:feature_class":"P",
    "gn:feature_code":"PPL",
    "gn:name":"Tiaba",
    "gn:population":0,
    "gn:timezone":"Africa/Banjul",
    "iso:country":"GM",
    "wof:name":"Tiaba",
    "wof:placetype":"locality"
},
  "geometry": {"coordinates":[-16.04889,13.59389],"type":"Point"}
}