{
  "type": "Feature",
  "properties": {
    "gn:admin1_code":"04",
    "gn:asciiname":"Sare Demba",
    "gn:country_code":"GM",
    "gn:dem":33,
    "gn:feature_class":"P",
    "gn:feature_code":"PPL",
    "gn:name":"Sare Demba",
    "gn:population":0,
    "gn:timezone":"Africa/Banjul",
    "iso:country":"GM",
    "wof:name":"Sare Demba",
    "wof:placetype":"locality"
},
  "geometry": {"coordinates":[-14.31667,13.43333],"type":"Point"}
}