{
  "type": "Feature",
  "properties": {
    "gn:admin1_code":"05",
    "gn:asciiname":"Cape Point",
    "gn:country_code":"GM",
    "gn:dem":-9999,
    "gn:feature_class":"P",
    "gn:feature_code":"PPL",
    "gn:name":"Cape Point",
    "gn:population":0,
    "gn:timezone":"Africa/Banjul",
    "iso:country":"GM",
    "name:afr_x_preferred":[
        "Kaappunt"
    ],
    "name:aze_x_preferred":[
        "Keyp-Poynt burnu"
    ],
    "name:bul_x_preferred":[
        "\u041a\u0435\u0439\u043f \u041f\u043e\u0439\u043d\u0442"
    ],
    "name:cat_x_preferred":[
        "Cap Point"
    ],
    "name:ceb_x_preferred":[
        "Cape Point"
    ],
    "name:ces_x_preferred":[
        "Cape Point"
    ],
    "name:deu_x_preferred":[
        "Cape Point"
    ],
    "name:fin_x_preferred":[
        "Cape Point"
    ],
    "name:fra_x_preferred":[
        "Cape Point"
    ],
    "name:hin_x_preferred":[
        "\u0915\u0947\u092a \u092a\u094d\u0935\u093e\u0907\u0902\u091f"
    ],
    "name:hye_x_preferred":[
        "\u0554\u0565\u0575\u0583 \u0553\u0578\u0575\u0576\u0569"
    ],
    "name:kat_x_preferred":[
        "\u10d9\u10d4\u10d8\u10de-\u10de\u10dd\u10d8\u10dc\u10e2\u10d8"
    ],
    "name:kbd_x_preferred":[
        "\u041a\u0435\u0439\u043f-\u041f\u043e\u0439\u043d\u0442"
    ],
    "name:ltz_x_preferred":[
        "Kap Point"
    ],
    "name:nld_x_preferred":[
        "Cape Point"
    ],
    "name:nor_x_preferred":[
        "Cape Point"
    ],
    "name:pol_x_preferred":[
        "Cape Point"
    ],
    "name:rus_x_preferred":[
        "\u041a\u0435\u0439\u043f-\u041f\u043e\u0439\u043d\u0442"
    ],
    "name:slk_x_preferred":[
        "Cape Point"
    ],
    "name:spa_x_preferred":[
        "Cabo Point"
    ],
    "name:swe_x_preferred":[
        "Kapudden"
    ],
    "name:tam_x_preferred":[
        "\u0b95\u0bc7\u0baa\u0bcd \u0bae\u0bc1\u0ba9\u0bc8"
    ],
    "name:ukr_x_preferred":[
        "\u041a\u0435\u0439\u043f-\u041f\u043e\u0457\u043d\u0442"
    ],
    "name:und_x_variant":[
        "Cape Saint Mary",
        "Cap Sainte Marie",
        "Cape Point"
    ],
    "wof:name":"Cape Point",
    "wof:placetype":"locality"
},
  "geometry": {"coordinates":[-16.66917,13.48917],"type":"Point"}
}