{
  "type": "Feature",
  "properties": {
    "gn:admin1_code":"05",
    "gn:asciiname":"Cape Point",
    "gn:country_code":"GM",
    "gn:dem":-9999,
    "gn:feature_class":"P",
    "gn:feature_code":"PPL",
    "gn:name":"Cape Point",
    "gn:population":0,
    "gn:timezone":"Africa/Banjul",
    "iso:country":"GM",
    "name:und_x_variant":[
        "Cape Saint Mary",
        "Cap Sainte Marie",
        "Cape Point"
    ],
    "wof:name":"Cape Point",
    "wof:placetype":"locality"
},
  "geometry": {"coordinates":[-16.66917,13.48917],"type":"Point"}
}