{
  "type": "Feature",
  "properties": {
    "gn:country":"GM",
    "gn:fcode":"PPL",
    "gn:pop":212,
    "iso:country":"GM",
    "qs:name":"Mbamori Kunda",
    "qs:photos_9r":0,
    "qs:photos_sr":0,
    "qs:pop_sr":"2",
    "wof:name":"Mbamori Kunda",
    "wof:placetype":"locality",
    "wof:population":212
},
  "geometry": {"coordinates":[-16.00361,13.58167],"type":"Point"}
}