{
  "type": "Feature",
  "properties": {
    "gn:admin1_code":"02",
    "gn:asciiname":"Banniba Jonki",
    "gn:country_code":"GM",
    "gn:dem":39,
    "gn:feature_class":"P",
    "gn:feature_code":"PPL",
    "gn:name":"Banniba Jonki",
    "gn:population":0,
    "gn:timezone":"Africa/Banjul",
    "iso:country":"GM",
    "name:und_x_variant":[
        "Bani Bajenko",
        "Banniba Jonki"
    ],
    "wof:name":"Banniba Jonki",
    "wof:placetype":"locality"
},
  "geometry": {"coordinates":[-15.23333,13.41667],"type":"Point"}
}