{
  "type": "Feature",
  "properties": {
    "gn:admin1_code":"05",
    "gn:asciiname":"Bondali Jola",
    "gn:country_code":"GM",
    "gn:dem":22,
    "gn:feature_class":"P",
    "gn:feature_code":"PPL",
    "gn:name":"Bondali Jola",
    "gn:population":0,
    "gn:timezone":"Africa/Banjul",
    "iso:country":"GM",
    "wof:name":"Bondali Jola",
    "wof:placetype":"locality"
},
  "geometry": {"coordinates":[-16.01667,13.23333],"type":"Point"}
}