{
  "type": "Feature",
  "properties": {
    "gn:admin1_code":"02",
    "gn:asciiname":"Wulumisa",
    "gn:country_code":"GM",
    "gn:dem":7,
    "gn:feature_class":"P",
    "gn:feature_code":"PPL",
    "gn:name":"Wulumisa",
    "gn:population":0,
    "gn:timezone":"Africa/Banjul",
    "iso:country":"GM",
    "name:und_x_variant":[
        "Willimissa",
        "Wulumisa"
    ],
    "wof:name":"Wulumisa",
    "wof:placetype":"locality"
},
  "geometry": {"coordinates":[-16.11667000000001,13.41667],"type":"Point"}
}