{
  "type": "Feature",
  "properties": {
    "gn:admin1_code":"07",
    "gn:asciiname":"Suarra Kunda",
    "gn:cc2":"GM",
    "gn:country_code":"GM",
    "gn:dem":12,
    "gn:feature_class":"P",
    "gn:feature_code":"PPL",
    "gn:name":"Suarra Kunda",
    "gn:population":0,
    "gn:timezone":"Africa/Banjul",
    "iso:country":"GM",
    "name:und_x_variant":[
        "Suara Kunda",
        "Suarra Kunda"
    ],
    "wof:name":"Suarra Kunda",
    "wof:placetype":"locality"
},
  "geometry": {"coordinates":[-16.08222,13.50694],"type":"Point"}
}