{
  "type": "Feature",
  "properties": {
    "gn:admin1_code":"07",
    "gn:asciiname":"Ker Gumalo",
    "gn:country_code":"GM",
    "gn:dem":31,
    "gn:feature_class":"P",
    "gn:feature_code":"PPL",
    "gn:name":"Ker Gumalo",
    "gn:population":0,
    "gn:timezone":"Africa/Banjul",
    "iso:country":"GM",
    "wof:name":"Ker Gumalo",
    "wof:placetype":"locality"
},
  "geometry": {"coordinates":[-15.86667,13.58333],"type":"Point"}
}