{
  "type": "Feature",
  "properties": {
    "gn:admin1_code":"05",
    "gn:asciiname":"Suma Kunda Koto",
    "gn:cc2":"GM",
    "gn:country_code":"GM",
    "gn:dem":12,
    "gn:feature_class":"P",
    "gn:feature_code":"PPL",
    "gn:name":"Suma Kunda Koto",
    "gn:population":0,
    "gn:timezone":"Africa/Banjul",
    "iso:country":"GM",
    "name:und_x_variant":[
        "Suma Kunda",
        "Suma Kunda Koto"
    ],
    "wof:name":"Suma Kunda Koto",
    "wof:placetype":"locality"
},
  "geometry": {"coordinates":[-16.49333,13.22667],"type":"Point"}
}