{
  "type": "Feature",
  "properties": {
    "gn:admin1_code":"03",
    "gn:asciiname":"Jalo Kunda Sering Ceesay",
    "gn:country_code":"GM",
    "gn:dem":46,
    "gn:feature_class":"P",
    "gn:feature_code":"PPL",
    "gn:name":"Jalo Kunda Sering Ceesay",
    "gn:population":0,
    "gn:timezone":"Africa/Banjul",
    "iso:country":"GM",
    "wof:name":"Jalo Kunda Sering Ceesay",
    "wof:placetype":"locality"
},
  "geometry": {"coordinates":[-14.98333,13.75],"type":"Point"}
}