{
  "type": "Feature",
  "properties": {
    "gn:admin1_code":"03",
    "gn:asciiname":"Ker Bamba",
    "gn:country_code":"GM",
    "gn:dem":17,
    "gn:feature_class":"P",
    "gn:feature_code":"PPL",
    "gn:name":"Ker Bamba",
    "gn:population":0,
    "gn:timezone":"Africa/Banjul",
    "iso:country":"GM",
    "wof:name":"Ker Bamba",
    "wof:placetype":"locality"
},
  "geometry": {"coordinates":[-15.16667,13.61667],"type":"Point"}
}