{
  "type": "Feature",
  "properties": {
    "gn:admin1_code":"04",
    "gn:asciiname":"Yarobawal",
    "gn:country_code":"GM",
    "gn:dem":39,
    "gn:feature_class":"P",
    "gn:feature_code":"PPL",
    "gn:name":"Yarobawal",
    "gn:population":0,
    "gn:timezone":"Africa/Banjul",
    "iso:country":"GM",
    "name:und_x_variant":[
        "Yorubawal",
        "Yarobawal"
    ],
    "wof:name":"Yarobawal",
    "wof:placetype":"locality"
},
  "geometry": {"coordinates":[-14.21667,13.43333],"type":"Point"}
}