{
  "type": "Feature",
  "properties": {
    "gn:admin1_code":"02",
    "gn:asciiname":"Burrong",
    "gn:cc2":"GM",
    "gn:country_code":"GM",
    "gn:dem":12,
    "gn:feature_class":"P",
    "gn:feature_code":"PPL",
    "gn:name":"Burrong",
    "gn:population":0,
    "gn:timezone":"Africa/Banjul",
    "iso:country":"GM",
    "name:und_x_variant":[
        "Birong",
        "Burrong"
    ],
    "wof:name":"Burrong",
    "wof:placetype":"locality"
},
  "geometry": {"coordinates":[-16.17944,13.32667],"type":"Point"}
}