{
  "type": "Feature",
  "properties": {
    "gn:admin1_code":"04",
    "gn:asciiname":"Sinchu Sambar",
    "gn:country_code":"GM",
    "gn:dem":52,
    "gn:feature_class":"P",
    "gn:feature_code":"PPL",
    "gn:name":"Sinchu Sambar",
    "gn:population":0,
    "gn:timezone":"Africa/Banjul",
    "iso:country":"GM",
    "wof:name":"Sinchu Sambar",
    "wof:placetype":"locality"
},
  "geometry": {"coordinates":[-14.18333,13.51667],"type":"Point"}
}