{
  "type": "Feature",
  "properties": {
    "gn:admin1_code":"04",
    "gn:asciiname":"Dasilami",
    "gn:country_code":"GM",
    "gn:dem":51,
    "gn:feature_class":"P",
    "gn:feature_code":"PPL",
    "gn:name":"Dasilami",
    "gn:population":0,
    "gn:timezone":"Africa/Banjul",
    "iso:country":"GM",
    "wof:name":"Dasilami",
    "wof:placetype":"locality"
},
  "geometry": {"coordinates":[-13.95,13.51667],"type":"Point"}
}