{
  "type": "Feature",
  "properties": {
    "gn:admin1_code":"07",
    "gn:asciiname":"Madina Bafuloto",
    "gn:country_code":"GM",
    "gn:dem":30,
    "gn:feature_class":"P",
    "gn:feature_code":"PPL",
    "gn:name":"Madina Bafuloto",
    "gn:population":0,
    "gn:timezone":"Africa/Banjul",
    "iso:country":"GM",
    "name:und_x_variant":[
        "Chermo Omar",
        "Cherno Omar",
        "Madina Bafuloto"
    ],
    "wof:name":"Madina Bafuloto",
    "wof:placetype":"locality"
},
  "geometry": {"coordinates":[-16.33972,13.45583],"type":"Point"}
}