{
  "type": "Feature",
  "properties": {
    "gn:admin1_code":"04",
    "gn:asciiname":"Samba Jowala",
    "gn:country_code":"GM",
    "gn:dem":2,
    "gn:feature_class":"P",
    "gn:feature_code":"PPL",
    "gn:name":"Samba Jowala",
    "gn:population":0,
    "gn:timezone":"Africa/Banjul",
    "iso:country":"GM",
    "wof:name":"Samba Jowala",
    "wof:placetype":"locality"
},
  "geometry": {"coordinates":[-14.31667,13.31667],"type":"Point"}
}