{
  "type": "Feature",
  "properties": {
    "gn:admin1_code":"05",
    "gn:asciiname":"Tampoto",
    "gn:country_code":"GM",
    "gn:dem":32,
    "gn:feature_class":"P",
    "gn:feature_code":"PPL",
    "gn:name":"Tampoto",
    "gn:population":0,
    "gn:timezone":"Africa/Banjul",
    "iso:country":"GM",
    "wof:name":"Tampoto",
    "wof:placetype":"locality"
},
  "geometry": {"coordinates":[-16.26222000000001,13.20667],"type":"Point"}
}