{
  "type": "Feature",
  "properties": {
    "gn:admin1_code":"05",
    "gn:asciiname":"Deya",
    "gn:country_code":"GM",
    "gn:dem":19,
    "gn:feature_class":"P",
    "gn:feature_code":"PPL",
    "gn:name":"Deya",
    "gn:population":0,
    "gn:timezone":"Africa/Banjul",
    "iso:country":"GM",
    "name:ceb_x_preferred":[
        "Deya"
    ],
    "name:swe_x_preferred":[
        "Deya"
    ],
    "wof:name":"Deya",
    "wof:placetype":"locality"
},
  "geometry": {"coordinates":[-16.73611,13.26472],"type":"Point"}
}