{
  "type": "Feature",
  "properties": {
    "gn:country":"GM",
    "gn:fcode":"PPL",
    "gn:population":709,
    "iso:country":"GM",
    "qs:name":"Mara Magai",
    "qs:photos_9r":0,
    "qs:photos_sr":0,
    "qs:pop_sr":"2",
    "wof:name":"Mara Magai",
    "wof:placetype":"locality",
    "wof:population":709
},
  "geometry": {"coordinates":[-14.91667,13.51667],"type":"Point"}
}