{
  "type": "Feature",
  "properties": {
    "gn:country":"GM",
    "gn:fcode":"PPL",
    "gn:pop":39,
    "iso:country":"GM",
    "qs:name":"Jombiya",
    "qs:photos_9r":0,
    "qs:photos_sr":0,
    "qs:pop_sr":"1",
    "wof:name":"Jombiya",
    "wof:placetype":"locality",
    "wof:population":39
},
  "geometry": {"coordinates":[-16.73333,13.21667],"type":"Point"}
}